localsandbox/__init__.py
localsandbox/core.py
localsandbox/exceptions.py
localsandbox/shim/deno.json
localsandbox/shim/deno.lock
localsandbox/shim/src/cli.ts
localsandbox/shim/src/python-runner.ts
localsandbox/shim/src/python.ts
localsandbox-0.1.1.dist-info/WHEEL
localsandbox-0.1.1.dist-info/METADATA
localsandbox-0.1.1.dist-info/RECORD
