Metadata-Version: 2.3
Name: localsandbox
Version: 0.1.1
Summary: A python SDK for a agentfs + just-bash + pyodide agent sandbox.
Requires-Python: >=3.12
